{
  "categories": [
    {
      "title": "Mobile Development",
      "skills": [
        {
          "name": "Flutter",
          "level": 2,
          "icon": "skill-icons:flutter-dark"
        },
        {
          "name": "Dart",
          "level": 2,
          "icon": "skill-icons:dart-dark"
        },
        {
          "name": "Kotlin",
          "level": 1,
          "icon": "skill-icons:kotlin-dark"
        },
        {
          "name": "Compose Multiplatform",
          "level": 2,
          "icon": "devicon-plain:kotlin"
        }
      ]
    },
    {
      "title": "Frontend",
      "skills": [
        {
          "name": "Astro",
          "level": 2,
          "icon": "skill-icons:astro"
        },
        {
          "name": "HTML",
          "level": 3,
          "icon": "skill-icons:html"
        },
        {
          "name": "CSS",
          "level": 3,
          "icon": "skill-icons:css"
        },
        {
          "name": "Tailwind CSS",
          "level": 3,
          "icon": "skill-icons:tailwindcss-dark"
        },
        {
          "name": "Bootstrap",
          "level": 3,
          "icon": "devicon-plain:bootstrap"
        },
        {
          "name": "Next JS",
          "level": 2,
          "icon": "skill-icons:nextjs-dark"
        },
        {
          "name": "React JS",
          "level": 2,
          "icon": "skill-icons:react-dark"
        },
        {
          "name": "Jquery",
          "level": 3,
          "icon": "devicon-plain:jquery"
        }
      ]
    },
    {
      "title": "Backend",
      "skills": [
        {
          "name": "FastAPI",
          "level": 2,
          "icon": "skill-icons:fastapi"
        },
        {
          "name": "NestJS",
          "level": 2,
          "icon": "skill-icons:nestjs-dark"
        },
        {
          "name": "Golang",
          "level": 2,
          "icon": "skill-icons:golang"
        },
        {
          "name": "Python",
          "level": 2,
          "icon": "skill-icons:python-dark"
        },
        {
          "name": "Firebase",
          "level": 2,
          "icon": "vscode-icons:file-type-firebase"
        },
        {
          "name": "Node JS",
          "level": 2,
          "icon": "skill-icons:nodejs-dark"
        },
        {
          "name": "PHP",
          "level": 3,
          "icon": "skill-icons:php-dark"
        },
        {
          "name": "Laravel",
          "level": 3,
          "icon": "skill-icons:laravel-dark"
        }
      ]
    },
    {
      "title": "Database",
      "skills": [
        {
          "name": "Prisma",
          "level": 2,
          "icon": "skill-icons:prisma"
        },
        {
          "name": "SQLite",
          "level": 3,
          "icon": "skill-icons:sqlite"
        },
        {
          "name": "PostgreSQL",
          "level": 3,
          "icon": "skill-icons:postgresql-dark"
        },
        {
          "name": "MySQL",
          "level": 3,
          "icon": "skill-icons:mysql-dark"
        },
        {
          "name": "MongoDB",
          "level": 2,
          "icon": "skill-icons:mongodb"
        },
        {
          "name": "Supabase",
          "level": 2,
          "icon": "devicon-plain:supabase"
        },
        {
          "name": "SQL Server",
          "level": 2,
          "icon": "devicon-plain:microsoftsqlserver"
        }
      ]
    },
    {
      "title": "DevOps",
      "skills": [
        {
          "name": "Docker",
          "level": 2,
          "icon": "skill-icons:docker"
        },
        {
          "name": "Jenkins",
          "level": 2,
          "icon": "devicon-plain:jenkins"
        }
      ]
    },
    {
      "title": "Tools",
      "skills": [
        {
          "name": "Git",
          "level": 3,
          "icon": "skill-icons:git"
        },
        {
          "name": "GitHub",
          "level": 3,
          "icon": "skill-icons:github-dark"
        }
      ]
    }
  ]
}